purl2src/__init__.py
purl2src/__main__.py
purl2src/cli.py
purl2src/parser.py
purl2src/handlers/__init__.py
purl2src/handlers/base.py
purl2src/handlers/cargo.py
purl2src/handlers/conda.py
purl2src/handlers/generic.py
purl2src/handlers/github.py
purl2src/handlers/golang.py
purl2src/handlers/maven.py
purl2src/handlers/npm.py
purl2src/handlers/nuget.py
purl2src/handlers/pypi.py
purl2src/handlers/rubygems.py
purl2src/utils/__init__.py
purl2src/utils/cache.py
purl2src/utils/http.py
semantic_copycat_purl2src-1.2.2.dist-info/licenses/LICENSE
semantic_copycat_purl2src-1.2.2.dist-info/METADATA
semantic_copycat_purl2src-1.2.2.dist-info/WHEEL
semantic_copycat_purl2src-1.2.2.dist-info/entry_points.txt
semantic_copycat_purl2src-1.2.2.dist-info/top_level.txt
semantic_copycat_purl2src-1.2.2.dist-info/RECORD
