Metadata-Version: 2.4
Name: semantic-copycat-purl2src
Version: 1.2.2
Summary: Translate Package URLs (PURLs) into validated download URLs for source code artifacts
Author-email: "Oscar Valenzuela B." <oscar.valenzuela.b@gmail.com>
License: Apache-2.0
Project-URL: Homepage, https://github.com/oscarvalenzuelab/semantic-copycat-purl2src
Project-URL: Documentation, https://github.com/oscarvalenzuelab/semantic-copycat-purl2src#readme
Project-URL: Repository, https://github.com/oscarvalenzuelab/semantic-copycat-purl2src
Project-URL: Issues, https://github.com/oscarvalenzuelab/semantic-copycat-purl2src/issues
Keywords: purl,package-url,package-manager,source-code,license-compliance,ai-detection,semantic-analysis,semantic-copycat,code-copycat
Classifier: Development Status :: 3 - Alpha
Classifier: Intended Audience :: Developers
Classifier: License :: OSI Approved :: Apache Software License
Classifier: Programming Language :: Python :: 3
Classifier: Programming Language :: Python :: 3.8
Classifier: Programming Language :: Python :: 3.9
Classifier: Programming Language :: Python :: 3.10
Classifier: Programming Language :: Python :: 3.11
Classifier: Programming Language :: Python :: 3.12
Classifier: Topic :: Software Development :: Libraries :: Python Modules
Classifier: Topic :: System :: Software Distribution
Requires-Python: >=3.8
License-File: LICENSE
Requires-Dist: click>=8.0.0
Requires-Dist: requests>=2.28.0
Requires-Dist: urllib3>=2.5.0
Provides-Extra: dev
Requires-Dist: pytest>=7.0.0; extra == "dev"
Requires-Dist: pytest-cov>=4.0.0; extra == "dev"
Requires-Dist: pytest-mock>=3.10.0; extra == "dev"
Requires-Dist: black>=23.0.0; extra == "dev"
Requires-Dist: flake8>=6.0.0; extra == "dev"
Requires-Dist: mypy>=1.0.0; extra == "dev"
Requires-Dist: types-requests>=2.28.0; extra == "dev"
Requires-Dist: tox>=4.0.0; extra == "dev"
Dynamic: license-file
